topsis/topsis.py
topsis_101803128/__init__.py
topsis_101803128/topsis.py
topsis_101803128-1.4.dist-info/LICENSE
topsis_101803128-1.4.dist-info/METADATA
topsis_101803128-1.4.dist-info/WHEEL
topsis_101803128-1.4.dist-info/top_level.txt
topsis_101803128-1.4.dist-info/RECORD
