Metadata-Version: 2.1
Name: topsis-101803128
Version: 1.4
Summary: A Python package implementing TOPSIS technique.
Home-page: https://github.com/Divyamdj/Topsis-Pypi-Package
Author: Divyam Jain
Author-email: divyamvswild@gmail.com
License: MIT
Download-URL: https://github.com/Divyamdj/Topsis-Pypi-Package/archive/v1.4.tar.gz
Keywords: Topsis,Topsis Ranking
Platform: UNKNOWN
Classifier: Development Status :: 3 - Alpha
Classifier: Intended Audience :: Developers
Classifier: Topic :: Software Development :: Build Tools
Classifier: License :: OSI Approved :: MIT License
Classifier: Programming Language :: Python :: 3.6
Classifier: Programming Language :: Python :: 3.7
Classifier: Programming Language :: Python :: 3.8
Requires-Dist: numpy
Requires-Dist: pandas
